diffmanifests/__init__.py
diffmanifests/__main__.py
diffmanifests/main.py
diffmanifests/cmd/__init__.py
diffmanifests/cmd/argument.py
diffmanifests/cmd/banner.py
diffmanifests/cmd/version.py
diffmanifests/config/config.json
diffmanifests/differ/__init__.py
diffmanifests/differ/differ.py
diffmanifests/gerrit/__init__.py
diffmanifests/gerrit/gerrit.py
diffmanifests/gitiles/__init__.py
diffmanifests/gitiles/gitiles.py
diffmanifests/logger/__init__.py
diffmanifests/logger/logger.py
diffmanifests/printer/__init__.py
diffmanifests/printer/printer.py
diffmanifests/proto/__init__.py
diffmanifests/proto/proto.py
diffmanifests/querier/__init__.py
diffmanifests/querier/querier.py
diffmanifests-3.7.9.dist-info/licenses/LICENSE
diffmanifests-3.7.9.dist-info/METADATA
diffmanifests-3.7.9.dist-info/WHEEL
diffmanifests-3.7.9.dist-info/entry_points.txt
diffmanifests-3.7.9.dist-info/top_level.txt
diffmanifests-3.7.9.dist-info/RECORD
