Metadata-Version: 2.4
Name: diffmanifests
Version: 3.7.9
Summary: Diff Manifests via Gitiles API
Home-page: https://github.com/craftslab/diffmanifests
Download-URL: https://github.com/craftslab/diffmanifests/archive/v3.7.9.tar.gz
Author: Jia Jia
Author-email: angersax@sina.com
License: Apache-2.0
Keywords: diff,manifests,gitiles,api
Classifier: Programming Language :: Python :: 3
Classifier: License :: OSI Approved :: Apache Software License
Classifier: Operating System :: OS Independent
License-File: LICENSE
Requires-Dist: colorama
Requires-Dist: openpyxl
Requires-Dist: requests
Requires-Dist: xmltodict
Provides-Extra: dev
Requires-Dist: coverage; extra == "dev"
Requires-Dist: coveralls; extra == "dev"
Requires-Dist: pytest; extra == "dev"
Requires-Dist: setuptools; extra == "dev"
Requires-Dist: twine; extra == "dev"
Requires-Dist: wheel; extra == "dev"
Dynamic: author
Dynamic: author-email
Dynamic: classifier
Dynamic: description
Dynamic: description-content-type
Dynamic: download-url
Dynamic: home-page
Dynamic: keywords
Dynamic: license
Dynamic: license-file
Dynamic: provides-extra
Dynamic: requires-dist
Dynamic: summary
